lgt_jobs/__init__.py
lgt_jobs/basejobs.py
lgt_jobs/env.py
lgt_jobs/main.py
lgt_jobs/runner.py
lgt_jobs/simple_job.py
lgt_jobs/smtp.py
lgt_jobs/assets/images/arrow.png
lgt_jobs/assets/images/arrow_blue.png
lgt_jobs/assets/images/firework.png
lgt_jobs/assets/images/lock.png
lgt_jobs/assets/images/logo.png
lgt_jobs/assets/images/mail.png
lgt_jobs/jobs/__init__.py
lgt_jobs/jobs/analytics.py
lgt_jobs/jobs/bot_stats_update.py
lgt_jobs/jobs/bots_killer.py
lgt_jobs/jobs/chat_history.py
lgt_jobs/jobs/connect_sources.py
lgt_jobs/jobs/inbox_leads.py
lgt_jobs/jobs/load_slack_people.py
lgt_jobs/jobs/load_slack_users.py
lgt_jobs/jobs/mass_message.py
lgt_jobs/jobs/send_code.py
lgt_jobs/jobs/send_slack_invites.py
lgt_jobs/jobs/send_slack_message.py
lgt_jobs/jobs/update_slack_profile.py
lgt_jobs/jobs/workspace_connect.py
lgt_jobs/lgt_common/__init__.py
lgt_jobs/lgt_common/helpers.py
lgt_jobs/lgt_common/discord_client/__init__.py
lgt_jobs/lgt_common/discord_client/discord_client.py
lgt_jobs/lgt_common/discord_client/methods.py
lgt_jobs/lgt_common/enums/__init__.py
lgt_jobs/lgt_common/enums/slack_errors.py
lgt_jobs/lgt_common/pubsub/__init__.py
lgt_jobs/lgt_common/pubsub/messages.py
lgt_jobs/lgt_common/pubsub/pubsubfactory.py
lgt_jobs/lgt_common/slack_client/__init__.py
lgt_jobs/lgt_common/slack_client/methods.py
lgt_jobs/lgt_common/slack_client/slack_client.py
lgt_jobs/lgt_common/slack_client/web_client.py
lgt_jobs/lgt_data/__init__.py
lgt_jobs/lgt_data/analytics.py
lgt_jobs/lgt_data/engine.py
lgt_jobs/lgt_data/enums.py
lgt_jobs/lgt_data/helpers.py
lgt_jobs/lgt_data/model.py
lgt_jobs/lgt_data/mongo_repository.py
lgt_jobs/lgt_data/models/__init__.py
lgt_jobs/lgt_data/models/base.py
lgt_jobs/lgt_data/models/boards/__init__.py
lgt_jobs/lgt_data/models/boards/board.py
lgt_jobs/lgt_data/models/boards/status.py
lgt_jobs/lgt_data/models/bots/__init__.py
lgt_jobs/lgt_data/models/bots/base_bot.py
lgt_jobs/lgt_data/models/bots/bot_info.py
lgt_jobs/lgt_data/models/bots/dedicated_bot.py
leadguru_jobs-0.760.0.dist-info/METADATA
leadguru_jobs-0.760.0.dist-info/WHEEL
leadguru_jobs-0.760.0.dist-info/top_level.txt
leadguru_jobs-0.760.0.dist-info/RECORD
